dtleads_api_helper/__init__.py
dtleads_api_helper/dtl_controllers/__init__.py
dtleads_api_helper/dtl_controllers/dtl_account_controller.py
dtleads_api_helper/dtl_controllers/dtl_campaigns_controller.py
dtleads_api_helper/dtl_controllers/dtl_campaignsequences_controller.py
dtleads_api_helper/dtl_controllers/dtl_companies_controller.py
dtleads_api_helper/dtl_controllers/dtl_companylogs_controller.py
dtleads_api_helper/dtl_controllers/dtl_messages_controller.py
dtleads_api_helper/dtl_controllers/dtl_prospects_controller.py
dtleads_api_helper/dtl_controllers/dtl_replytemplates_controller.py
dtleads_api_helper/dtl_controllers/dtl_settingrestrictions_controller.py
dtleads_api_helper/dtl_controllers/dtl_subscription_controller.py
dtleads_api_helper/dtl_controllers/dtl_templates_controller.py
dtleads_api_helper/dtl_controllers/dtl_templatesettings_controller.py
dtleads_api_helper/dtl_controllers/dtl_users_controller.py
dtleads_api_helper/dtl_models/__init__.py
dtleads_api_helper/dtl_models/dtl_account_models.py
dtleads_api_helper/dtl_models/dtl_campaign_models.py
dtleads_api_helper/dtl_models/dtl_campaignsequence_models.py
dtleads_api_helper/dtl_models/dtl_company_models.py
dtleads_api_helper/dtl_models/dtl_companylog_models.py
dtleads_api_helper/dtl_models/dtl_prospect_models.py
dtleads_api_helper/dtl_models/dtl_replytemplate_models.py
dtleads_api_helper/dtl_models/dtl_settingrestriction_models.py
dtleads_api_helper/dtl_models/dtl_template_models.py
dtleads_api_helper/dtl_models/dtl_templatesetting_models.py
dtleads_api_helper/dtl_models/dtl_user_models.py
dtleads_api_helper-0.0.2.dist-info/LICENSE.txt
dtleads_api_helper-0.0.2.dist-info/METADATA
dtleads_api_helper-0.0.2.dist-info/WHEEL
dtleads_api_helper-0.0.2.dist-info/top_level.txt
dtleads_api_helper-0.0.2.dist-info/RECORD
